colossus/__init__.py
colossus/defaults.py
colossus/settings.py
colossus/version.py
colossus/cosmology/__init__.py
colossus/cosmology/cosmology.py
colossus/cosmology/power_spectrum.py
colossus/halo/__init__.py
colossus/halo/concentration.py
colossus/halo/mass_adv.py
colossus/halo/mass_defs.py
colossus/halo/mass_so.py
colossus/halo/profile_base.py
colossus/halo/profile_composite.py
colossus/halo/profile_diemer23.py
colossus/halo/profile_dk14.py
colossus/halo/profile_einasto.py
colossus/halo/profile_hernquist.py
colossus/halo/profile_nfw.py
colossus/halo/profile_outer.py
colossus/halo/profile_spline.py
colossus/halo/splashback.py
colossus/lss/__init__.py
colossus/lss/bias.py
colossus/lss/mass_function.py
colossus/lss/peaks.py
colossus/tests/__init__.py
colossus/tests/run_tests.py
colossus/tests/test_colossus.py
colossus/tests/test_cosmology.py
colossus/tests/test_cosmology_power_spectrum.py
colossus/tests/test_halo_concentration.py
colossus/tests/test_halo_mass.py
colossus/tests/test_halo_profile.py
colossus/tests/test_halo_splashback.py
colossus/tests/test_lss_bias.py
colossus/tests/test_lss_mass_function.py
colossus/tests/test_lss_peaks.py
colossus/tests/test_utils.py
colossus/utils/__init__.py
colossus/utils/constants.py
colossus/utils/mcmc.py
colossus/utils/storage.py
colossus/utils/utilities.py
colossus-1.3.12.dist-info/licenses/LICENSE.txt
colossus-1.3.12.dist-info/METADATA
colossus-1.3.12.dist-info/WHEEL
colossus-1.3.12.dist-info/top_level.txt
colossus-1.3.12.dist-info/RECORD
